aioacaia/__init__.py
aioacaia/acaiascale.py
aioacaia/const.py
aioacaia/decode.py
aioacaia/exceptions.py
aioacaia/helpers.py
aioacaia/py.typed
aioacaia-0.1.18.dist-info/licenses/LICENSE
aioacaia-0.1.18.dist-info/METADATA
aioacaia-0.1.18.dist-info/WHEEL
aioacaia-0.1.18.dist-info/top_level.txt
aioacaia-0.1.18.dist-info/RECORD
