Metadata-Version: 2.4
Name: aioacaia
Version: 0.1.18
Summary: An async implementation of PyAcaia
Author-email: Josef Zweck <24647999+zweckj@users.noreply.github.com>
Maintainer-email: Josef Zweck <24647999+zweckj@users.noreply.github.com>
License-Expression: AGPL-3.0-only
Project-URL: Homepage, https://github.com/zweckj/aioacaia
Project-URL: Repository, https://github.com/zweckj/aioacaia
Project-URL: Documentation, https://github.com/zweckj/aioacaia
Keywords: Acaia,Bluetooth,api,async,client
Classifier: Development Status :: 5 - Production/Stable
Classifier: Framework :: AsyncIO
Classifier: Intended Audience :: Developers
Classifier: Natural Language :: English
Classifier: Programming Language :: Python
Classifier: Programming Language :: Python :: 3.12
Requires-Python: >=3.12
License-File: LICENSE
Requires-Dist: bleak>=0.20.2
Requires-Dist: bleak-retry-connector>=4.0.0
Provides-Extra: dev
Requires-Dist: covdefaults==2.3.0; extra == "dev"
Requires-Dist: coverage==7.6.7; extra == "dev"
Requires-Dist: syrupy==4.7.2; extra == "dev"
Requires-Dist: pytest==8.3.3; extra == "dev"
Requires-Dist: pytest-asyncio==0.24.0; extra == "dev"
Requires-Dist: pytest-cov==6.0.0; extra == "dev"
Dynamic: license-file
